README.md
setup.py
groceries/__init__.py
groceries/groceries.py
groceries/recipes.py
groceries/units.py
groceries/configs/__init__.py
groceries/configs/config_handler.py
groceries/configs/config_types.py
groceries/configs/constants/__init__.py
groceries/configs/constants/default.py
groceries/configs/language/__init__.py
groceries/configs/language/english.py
groceries/configs/language/norwegian.py
groceries/configs/menu_format/__init__.py
groceries/configs/menu_format/simple_text_menu.py
groceries/configs/settings/__init__.py
groceries/configs/settings/metric_imperial.py
groceries/configs/settings/metric_small.py
groceries/configs/unit_definition/__init__.py
groceries/configs/unit_definition/metric.py
groceries/configs/unit_definition/metric_imperial.py
groceries/configs/unit_definition/unit_constants.py
groceries/test/test_config_handler.py
groceries/test/test_groceries.py
groceries/test/test_recipes.py
groceries/test/test_units.py
groceries_tobiasli.egg-info/PKG-INFO
groceries_tobiasli.egg-info/SOURCES.txt
groceries_tobiasli.egg-info/dependency_links.txt
groceries_tobiasli.egg-info/requires.txt
groceries_tobiasli.egg-info/top_level.txt