Metadata-Version: 2.1
Name: groceries-tobiasli
Version: 1.1.7
Summary: Module for parsing shopping lists and dinner menus and compiling shopping lists.
Home-page: https://github.com/tobiasli/groceries
Author: Tobias Litherland
Author-email: tobiaslland@gmail.com
License: UNKNOWN
Platform: UNKNOWN
Classifier: Programming Language :: Python :: 3
Classifier: License :: OSI Approved :: MIT License
Classifier: Operating System :: OS Independent
